noteplan/__init__.py
noteplan/__main__.py
noteplan/callback.py
noteplan/constants.py
noteplan/convert.py
noteplan-0.2.0.dist-info/WHEEL
noteplan-0.2.0.dist-info/entry_points.txt
noteplan-0.2.0.dist-info/METADATA
noteplan-0.2.0.dist-info/RECORD
