Metadata-Version: 2.4
Name: noteplan
Version: 0.2.0
Summary: Helpers for interacting with NotePlan
Author: Paul Traylor
Author-email: Paul Traylor <kungfudiscomonkey@gmail.com>
License-Expression: MIT
Classifier: Development Status :: 3 - Alpha
Classifier: Programming Language :: Python :: 3.10
Classifier: Programming Language :: Python :: 3.11
Classifier: Programming Language :: Python :: 3.12
Classifier: Programming Language :: Python :: 3.13
Classifier: Programming Language :: Python :: 3.14
Classifier: Programming Language :: Python :: 3.15
Requires-Python: >=3.10
Project-URL: issues, https://codeberg.org/kfdm/python-noteplan/issues
Project-URL: source, https://codeberg.org/kfdm/python-noteplan
